{
  "name": "Simple menten model",
  "species": [
    {
      "name": "s1",
      "symbol": "s1"
    }
  ],
  "odes": [
    {
      "species": "s1",
      "equation": "-s1*v_max/(K_m + s1)",
      "observable": true,
      "parameters": {
        "v_max": {
          "name": "v_max",
          "symbol": "v_max",
          "value": "7. * katal",
          "constant": false
        },
        "K_m": {
          "name": "K_m",
          "symbol": "K_m",
          "value": "100. * molar",
          "constant": false
        }
      }
    }
  ],
  "parameters": [
    {
      "name": "v_max",
      "symbol": "v_max",
      "value": "7. * katal",
      "constant": false
    },
    {
      "name": "K_m",
      "symbol": "K_m",
      "value": "100. * molar",
      "constant": false
    }
  ]
}